constdb.py
constdb-4.1.0.dist-info/LICENSE.txt
constdb-4.1.0.dist-info/METADATA
constdb-4.1.0.dist-info/WHEEL
constdb-4.1.0.dist-info/top_level.txt
constdb-4.1.0.dist-info/RECORD
