Metadata-Version: 2.1
Name: constdb
Version: 4.1.0
Summary: A simple and fast read-only embedded key-value database
Home-page: https://github.com/Lalaland/constdb-python
Author: Ethan Steinberg
Author-email: ethan.steinberg@gmail.com
License: UNKNOWN
Project-URL: Source, https://github.com/Lalaland/constdb-python
Keywords: database embedded
Platform: UNKNOWN
Classifier: Development Status :: 3 - Alpha
Classifier: Intended Audience :: Developers
Classifier: Topic :: Database
Classifier: License :: OSI Approved :: MIT License
Classifier: Programming Language :: Python :: 3
Classifier: Programming Language :: Python :: 3.4
Classifier: Programming Language :: Python :: 3.5
Classifier: Programming Language :: Python :: 3.6
License-File: LICENSE.txt
